mpl_theme_tweaker/__init__.py
mpl_theme_tweaker/app_state.py
mpl_theme_tweaker/app_utils.py
mpl_theme_tweaker/figure.py
mpl_theme_tweaker/figure_window.py
mpl_theme_tweaker/main.py
mpl_theme_tweaker/mpl_utils.py
mpl_theme_tweaker/opengl.py
mpl_theme_tweaker/params_window.py
mpl_theme_tweaker/translation.py
mpl_theme_tweaker/assets/mpl-theme-tweaker.png
mpl_theme_tweaker/assets/fonts/DroidSans.ttf
mpl_theme_tweaker/assets/fonts/Font_Awesome_6_Free-Solid-900.otf
mpl_theme_tweaker/assets/fonts/Inconsolata-Medium.ttf
mpl_theme_tweaker/assets/fonts/NotoSansSC-Bold.ttf
mpl_theme_tweaker/assets/fonts/NotoSansSC-Regular.ttf
mpl_theme_tweaker/assets/fonts/NotoSansSC-SemiBold.ttf
mpl_theme_tweaker/assets/fonts/fontawesome-webfont.ttf
mpl_theme_tweaker/assets/fonts/Roboto/LICENSE.txt
mpl_theme_tweaker/assets/fonts/Roboto/Roboto-Bold.ttf
mpl_theme_tweaker/assets/fonts/Roboto/Roboto-BoldItalic.ttf
mpl_theme_tweaker/assets/fonts/Roboto/Roboto-Regular.ttf
mpl_theme_tweaker/assets/fonts/Roboto/Roboto-RegularItalic.ttf
mpl_theme_tweaker/assets/locale/en/LC_MESSAGES/messages.en.po
mpl_theme_tweaker/assets/locale/en/LC_MESSAGES/messages.mo
mpl_theme_tweaker/assets/locale/zh_CN/LC_MESSAGES/messages.mo
mpl_theme_tweaker/assets/locale/zh_CN/LC_MESSAGES/messages.zh.po
mpl_theme_tweaker/assets/marker/circle.png
mpl_theme_tweaker/assets/marker/diamond.png
mpl_theme_tweaker/assets/marker/hexagon1.png
mpl_theme_tweaker/assets/marker/hexagon2.png
mpl_theme_tweaker/assets/marker/hline.png
mpl_theme_tweaker/assets/marker/none.png
mpl_theme_tweaker/assets/marker/octagon.png
mpl_theme_tweaker/assets/marker/pentagon.png
mpl_theme_tweaker/assets/marker/pixel.png
mpl_theme_tweaker/assets/marker/plus.png
mpl_theme_tweaker/assets/marker/plus_unfilled.png
mpl_theme_tweaker/assets/marker/point.png
mpl_theme_tweaker/assets/marker/square.png
mpl_theme_tweaker/assets/marker/star.png
mpl_theme_tweaker/assets/marker/thin_diamond.png
mpl_theme_tweaker/assets/marker/tri_down.png
mpl_theme_tweaker-0.1.1.dist-info/licenses/LICENSE
mpl_theme_tweaker-0.1.1.dist-info/METADATA
mpl_theme_tweaker-0.1.1.dist-info/WHEEL
mpl_theme_tweaker-0.1.1.dist-info/entry_points.txt
mpl_theme_tweaker-0.1.1.dist-info/top_level.txt
mpl_theme_tweaker-0.1.1.dist-info/RECORD
