Metadata-Version: 2.4
Name: mpl-theme-tweaker
Version: 0.1.1
Summary: A GUI tool to tweak, preview, and manage matplotlib style sheets.
Author: pplotter
Author-email: pplotter@foxmail.com
License-Expression: MIT
Project-URL: Repository, https://github.com/pplotter/mpl-theme-tweaker
Classifier: Programming Language :: Python :: 3.13
Classifier: Operating System :: OS Independent
Classifier: Framework :: Matplotlib
Classifier: Topic :: Education
Classifier: Topic :: Scientific/Engineering
Classifier: Topic :: Scientific/Engineering :: Visualization
Classifier: Topic :: Software Development :: User Interfaces
Classifier: Development Status :: 4 - Beta
Classifier: Natural Language :: English
Classifier: Natural Language :: Chinese (Simplified)
Requires-Python: >=3.13
License-File: LICENSE
Requires-Dist: glfw>=2.10.0
Requires-Dist: imgui-bundle>=1.92.4
Requires-Dist: matplotlib>=3.10.7
Requires-Dist: pyopengl>=3.1.10
Dynamic: license-file
